knowing_machine/__init__.py
knowing_machine/githf.py
knowing_machine/machina.yaml
knowing_machine-0.0.3.dist-info/LICENSE
knowing_machine-0.0.3.dist-info/METADATA
knowing_machine-0.0.3.dist-info/WHEEL
knowing_machine-0.0.3.dist-info/top_level.txt
knowing_machine-0.0.3.dist-info/RECORD
