Metadata-Version: 2.1
Name: knowing-machine
Version: 0.0.3
Summary: The machine that knows the answers to all questions
Author-email: Alexander Fedotov <alex.fedotov@aol.com>
Project-URL: Homepage, https://github.com/knowing-machine/knowing-machine
Project-URL: Bug Tracker, https://github.com/org_name/knowing-machine/issues
Classifier: Programming Language :: Python :: 3
Classifier: License :: OSI Approved :: MIT License
Classifier: Operating System :: OS Independent
Requires-Python: >=3.10
License-File: LICENSE
